kdquery.py
KdQuery-0.2.2.dist-info/DESCRIPTION.rst
KdQuery-0.2.2.dist-info/METADATA
KdQuery-0.2.2.dist-info/RECORD
KdQuery-0.2.2.dist-info/WHEEL
KdQuery-0.2.2.dist-info/metadata.json
KdQuery-0.2.2.dist-info/top_level.txt
