Metadata-Version: 2.0
Name: KdQuery
Version: 0.2.2
Summary: Nearest point query for any kd-tree implementation
Home-page: https://github.com/DeVilhena-Paulo/KdQuery
Author: Paulo Emilio de Vilhena
Author-email: pevilhena2@gmail.com
License: Apache Software License
Keywords: kd-tree query
Platform: UNKNOWN
Classifier: Development Status :: 3 - Alpha
Classifier: Intended Audience :: Developers
Classifier: Topic :: Utilities
Classifier: License :: OSI Approved :: Apache Software License
Classifier: Programming Language :: Python :: 3
Classifier: Programming Language :: Python :: 3.3
Classifier: Programming Language :: Python :: 3.4
Classifier: Programming Language :: Python :: 3.5
